LICENSE
correpy/__init__.py
correpy/domain/__init__.py
correpy/domain/entities/__init__.py
correpy/domain/entities/brokerage_note.py
correpy/domain/entities/security.py
correpy/domain/entities/transaction.py
correpy/domain/enums.py
correpy/domain/exceptions.py
correpy/parsers/__init__.py
correpy/parsers/brokerage_notes/__init__.py
correpy/parsers/brokerage_notes/b3_parser/__init__.py
correpy/parsers/brokerage_notes/b3_parser/b3_parser.py
correpy/parsers/brokerage_notes/base_parser.py
correpy/parsers/brokerage_notes/brokerage_note_section.py
correpy/parsers/brokerage_notes/inter_parser/__init__.py
correpy/parsers/brokerage_notes/inter_parser/inter.py
correpy/parsers/brokerage_notes/nuinvest_parser/__init__.py
correpy/parsers/brokerage_notes/nuinvest_parser/nuinvest.py
correpy/parsers/brokerage_notes/parser_factory.py
correpy/parsers/brokerage_notes/word_rectangle.py
correpy/parsers/exceptions.py
correpy/parsers/fitz_parser.py
correpy/py.typed
correpy/utils.py
correpy-0.6.0.dist-info/LICENSE
correpy-0.6.0.dist-info/METADATA
correpy-0.6.0.dist-info/WHEEL
correpy-0.6.0.dist-info/RECORD
