Metadata-Version: 2.1
Name: correpy
Version: 0.6.0
Summary: CorrePy (Corretagem Python) é uma lib responsável por parsear notas de corretagem no padrão B3 (Sinacor) e retornar os dados no formato JSON.
Home-page: https://github.com/thiagosalvatore/correpy
License: Apache-2.0
Keywords: corretagem,parser,b3,nota de corretagem,imposto de renda
Author: Thiago  Salvatore
Author-email: thiago.salvatore@gmail.com
Requires-Python: >=3.8,<4.0
Classifier: License :: OSI Approved :: Apache Software License
Classifier: Programming Language :: Python :: 3
Classifier: Programming Language :: Python :: 3.8
Classifier: Programming Language :: Python :: 3.9
Classifier: Programming Language :: Python :: 3.10
Classifier: Programming Language :: Python :: 3.11
Classifier: Programming Language :: Python :: 3.12
Requires-Dist: PyMuPDF (>=1.23.9,<2.0.0)
Project-URL: Repository, https://github.com/thiagosalvatore/correpy
